matplotlib_pyodide_worker_contrib/__init__.py
matplotlib_pyodide_worker_contrib/browser_backend.py
matplotlib_pyodide_worker_contrib/html5_canvas_backend.py
matplotlib_pyodide_worker_contrib/wasm_backend.py
matplotlib_pyodide_worker_contrib/webworker_backend.py
matplotlib_pyodide_worker_contrib-1.1.2.dist-info/licenses/LICENSE
matplotlib_pyodide_worker_contrib-1.1.2.dist-info/METADATA
matplotlib_pyodide_worker_contrib-1.1.2.dist-info/WHEEL
matplotlib_pyodide_worker_contrib-1.1.2.dist-info/top_level.txt
matplotlib_pyodide_worker_contrib-1.1.2.dist-info/RECORD
