Metadata-Version: 2.4
Name: matplotlib-pyodide-worker-contrib
Version: 1.1.2
Summary: WebWorker backend for Matplotlib compatible with Pyodide
Author: Pyodide developers
License: Mozilla Public License Version 2.0
Project-URL: Homepage, https://github.com/josselinonduty/matplotlib-pyodide-worker-contrib
Project-URL: Bug Tracker, https://github.com/josselinonduty/matplotlib-pyodide-worker-contrib/issues
Classifier: Programming Language :: Python :: 3
Classifier: License :: OSI Approved :: Mozilla Public License 2.0 (MPL 2.0)
Classifier: Operating System :: OS Independent
Requires-Python: >=3.12
License-File: LICENSE
Provides-Extra: test
Requires-Dist: pytest-pyodide==0.56.2; extra == "test"
Requires-Dist: pytest-cov; extra == "test"
Requires-Dist: build>=1.0; extra == "test"
Dynamic: license-file
